coscmd/__init__.py
coscmd/cos_auth.py
coscmd/cos_client.py
coscmd/cos_cmd.py
coscmd/cos_comm.py
coscmd/cos_global.py
coscmd/cos_threadpool.py
coscmd/test.py
coscmd-1.8.4.4.dist-info/DESCRIPTION.rst
coscmd-1.8.4.4.dist-info/METADATA
coscmd-1.8.4.4.dist-info/RECORD
coscmd-1.8.4.4.dist-info/WHEEL
coscmd-1.8.4.4.dist-info/entry_points.txt
coscmd-1.8.4.4.dist-info/metadata.json
coscmd-1.8.4.4.dist-info/top_level.txt
