Metadata-Version: 2.0
Name: coscmd
Version: 1.8.4.4
Summary: simple command for cos
Home-page: https://www.qcloud.com/
Author: lewzylu
Author-email: 327874225@qq.com
License: MIT
Platform: UNKNOWN
Requires-Dist: argparse (>=1.4.0)
Requires-Dist: datetime (==4.2)
Requires-Dist: prettytable (==0.7)
Requires-Dist: pytz (==2017.2)
Requires-Dist: pyyaml (==3.12)
Requires-Dist: requests (>=2.12.4)
Requires-Dist: six (==1.11.0)
Requires-Dist: tqdm (==4.15.0)
